jeyoTools/__init__.py
jeyoTools/csv_tool.py
tests/__init__.py
tests/csv_tools_test.py
jeyoTools-1.0.1.dist-info/METADATA
jeyoTools-1.0.1.dist-info/WHEEL
jeyoTools-1.0.1.dist-info/top_level.txt
jeyoTools-1.0.1.dist-info/RECORD
