Metadata-Version: 2.1
Name: jeyoTools
Version: 1.0.1
Summary: 常用小工具方法封装
Home-page: 
Author: hongningning
Author-email: 837116808@qq.com
License: MIT-0
Requires-Python: >=3.9
